{"type": "Feature", "id": 12515039, "properties": {"woe:id": 12515039, "woe:parent_id": 1049648, "woe:name": "Moue Airport", "woe:placetype": 14, "woe:placetype_name": "Airport", "woe:lang": "ENG", "iso:country": "NC", "meta:provider": ["geoplanet:7.3.1", "geoplanet:7.3.2", "geoplanet:7.4.0", "geoplanet:7.4.1", "geoplanet:7.5.1", "geoplanet:7.5.2", "geoplanet:7.6.0", "geoplanet:7.8.1", "geoplanet:7.9.0", "geoplanet:7.10.0", "geoplanet:8.0.0", "woeplanet:8.0.0"], "meta:indexed": "2020-08-20T20:26:28.014348", "woe:alias_ENG_V": ["ILP Airport", "ILP"], "meta:updated": "2020-08-22T02:46:39.789198", "woe:hierarchy": {"continent": 24865674, "country": 23424903, "town": 0, "planet": 1, "county": 24551445, "suburb": 0, "state": 24549807, "region": 0, "localadmin": 0}, "woe:timezone_id": 28350958, "woe:hash": "rezp7h1tn115", "woe:centroid": [167.477905, -22.608999], "geom:latitude": -22.608999, "geom:longitude": 167.477905, "geom:hash": "rezp7h1tn115", "woe:latitude": -22.608999, "geom:centroid": [167.477905, -22.608999], "woe:longitude": 167.477905, "woe:repo": "woeplanet-airport-nc"}, "geometry": {"coordinates": [167.477905, -22.608999], "type": "Point"}}