{"type": "Feature", "id": 12515036, "geometry": {"type": "Point", "coordinates": [167.964203, -21.5021]}, "properties": {"woe:id": 12515036, "woe:parent_id": 1049689, "woe:name": "Loyalty Islands Airport", "woe:placetype": 14, "woe:placetype_name": "Airport", "woe:lang": "ENG", "iso:country": "NC", "meta:provider": ["geoplanet:7.3.1", "geoplanet:7.3.2", "geoplanet:7.4.0", "geoplanet:7.4.1", "geoplanet:7.5.1", "geoplanet:7.5.2", "geoplanet:7.6.0", "geoplanet:7.8.1", "geoplanet:7.9.0", "geoplanet:7.10.0", "geoplanet:8.0.0", "woeplanet:8.0.0"], "meta:indexed": "2020-08-20T20:26:28.011755", "woe:alias_ENG_V": ["MEE Airport", "MEE"], "meta:updated": "2020-10-14T11:40:21.010326", "woe:hierarchy": {"continent": 24865674, "country": 23424903, "town": 0, "planet": 1, "county": 24551442, "suburb": 0, "state": 24549805, "region": 0, "localadmin": 0}, "woe:timezone_id": 28350958, "woe:hash": "rspmwjev1w53", "woe:centroid": [167.964203, -21.5021], "geom:latitude": -21.5021, "geom:longitude": 167.964203, "geom:hash": "rspmwjev1w53", "woe:latitude": -21.5021, "geom:centroid": [167.964203, -21.5021], "woe:longitude": 167.964203, "woe:repo": "woeplanet-airport-nc", "geom:area": 0.0, "woe:scale": 19}}